embedia/__init__.py
embedia/agents/__init__.py
embedia/agents/tooluser.py
embedia/core/chatllm.py
embedia/core/embedding.py
embedia/core/llm.py
embedia/core/tokenizer.py
embedia/core/tool.py
embedia/core/vectordb.py
embedia/schema/agent.py
embedia/schema/message.py
embedia/schema/persona.py
embedia/schema/pubsub.py
embedia/schema/textdoc.py
embedia/schema/tool.py
embedia/schema/vectordb.py
embedia/tools/__init__.py
embedia/tools/fileops.py
embedia/tools/python.py
embedia/tools/terminal.py
embedia/utils/exceptions.py
embedia/utils/file_callback.py
embedia/utils/print_callback.py
embedia/utils/pubsub.py
embedia/utils/terminal_colors.py
embedia/utils/tokens.py
embedia/utils/typechecking.py
embedia-0.0.3.dist-info/METADATA
embedia-0.0.3.dist-info/WHEEL
embedia-0.0.3.dist-info/licenses/LICENSE
embedia-0.0.3.dist-info/RECORD
